HISTORY
LICENSE
MANIFEST.in
README
setup.cfg
setup.py
calchylus/__init__.hy
calchylus/__init__.py
calchylus/lambdas.hy
calchylus/macros.hy
calchylus.egg-info/PKG-INFO
calchylus.egg-info/SOURCES.txt
calchylus.egg-info/dependency_links.txt
calchylus.egg-info/requires.txt
calchylus.egg-info/top_level.txt
calchylus2/__init__.py