Metadata-Version: 1.1
Name: calchylus
Version: 0.1.25
Summary: Calchylus - Lambda Calculus with Hy
Home-page: https://github.com/markomanninen/calchylus
Author: Marko Manninen
Author-email: elonmedia@gmail.com
License: UNKNOWN
Download-URL: https://github.com/markomanninen/calchylus/archive/v0.1.25.tar.gz
Keywords: hylang,python,lisp,macros,dsl,lambda calculus,functional language
Platform: any
Classifier: Development Status :: 3 - Alpha
Classifier: Intended Audience :: Developers
Classifier: License :: OSI Approved :: MIT License
Classifier: Operating System :: OS Independent
Classifier: Programming Language :: Lisp
Classifier: Topic :: Software Development :: Libraries
